neurartist/__init__.py
neurartist/__main__.py
neurartist/_package_manager.py
neurartist/cli.py
neurartist/losses.py
neurartist/models.py
neurartist/utils.py
neurartist-0.4.1.dist-info/LICENSE
neurartist-0.4.1.dist-info/METADATA
neurartist-0.4.1.dist-info/WHEEL
neurartist-0.4.1.dist-info/entry_points.txt
neurartist-0.4.1.dist-info/top_level.txt
neurartist-0.4.1.dist-info/RECORD
